barre.py
barre-1.1.0.dist-info/LICENSE
barre-1.1.0.dist-info/METADATA
barre-1.1.0.dist-info/WHEEL
barre-1.1.0.dist-info/top_level.txt
barre-1.1.0.dist-info/RECORD
